{
    "admin/widget_def_options_cb_potw_widget.html": {
        "version_id": 13,
        "version_string": "1.0.3",
        "hash": "9a55df208508b96a933700291082dfda"
    },
    "public/cb_potw_hide_img.less": {
        "version_id": 13,
        "version_string": "1.0.3",
        "hash": "8b4d9a226f5814a8688e880ed040ea7c"
    },
    "public/cb_potw_index.html": {
        "version_id": 14,
        "version_string": "1.0.4",
        "hash": "8051257fcbd6fdc4a5ff35ca9d0ea74d"
    },
    "public/cb_potw_widget.html": {
        "version_id": 13,
        "version_string": "1.0.3",
        "hash": "c9e5e8cc7d474ef3ea03f574bffea12c"
    },
    "public/potw_watch_confirm.html": {
        "version_id": 14,
        "version_string": "1.0.4",
        "hash": "bfd096381287cca117ea43cf8d0c5280"
    }
}